{
  "week": "W26",
  "activity_id": "23359471642",
  "sport": "running",
  "name": "W13 - test 5km",
  "date": "2026-06-24",
  "start_time_utc": "2026-06-24T03:56:10.000Z",
  "start_time": "03:56:10",
  "type": "running",
  "laps": [
    {
      "lap": 1,
      "tempo": "00:06:00.614",
      "tempo_in_movimento": "00:06:00.000",
      "distanza_km": 1,
      "ascesa_m": 6,
      "discesa_m": 5,
      "passo_medio": "0:06:00",
      "passo_medio_in_movimento": "0:06:00",
      "passo_migliore": "0:05:08",
      "cadenza_media_pam": 176.0,
      "cadenza_max_pam": 193.0,
      "lunghezza_media_passo": 94.97999877929688,
      "fc_media_bpm": 137.0,
      "fc_max_bpm": 147.0,
      "temperatura_med": 29,
      "calorie": 68
    },
    {
      "lap": 2,
      "tempo": "00:05:54.418",
      "tempo_in_movimento": "00:05:54.000",
      "distanza_km": 1,
      "ascesa_m": 4,
      "discesa_m": 4,
      "passo_medio": "0:05:54",
      "passo_medio_in_movimento": "0:05:54",
      "passo_migliore": "0:05:44",
      "cadenza_media_pam": 175.3125,
      "cadenza_max_pam": 179.0,
      "lunghezza_media_passo": 96.57000122070313,
      "fc_media_bpm": 144.0,
      "fc_max_bpm": 149.0,
      "temperatura_med": 26,
      "calorie": 69
    },
    {
      "lap": 3,
      "tempo": "00:04:21.926",
      "tempo_in_movimento": "00:04:21.926",
      "distanza_km": 1,
      "ascesa_m": 0,
      "discesa_m": 5,
      "passo_medio": "0:04:21",
      "passo_medio_in_movimento": "0:04:21",
      "passo_migliore": "0:04:02",
      "cadenza_media_pam": 188.28125,
      "cadenza_max_pam": 192.0,
      "lunghezza_media_passo": 120.5199951171875,
      "fc_media_bpm": 160.0,
      "fc_max_bpm": 164.0,
      "temperatura_med": 24,
      "calorie": 60
    },
    {
      "lap": 4,
      "tempo": "00:04:24.230",
      "tempo_in_movimento": "00:04:24.230",
      "distanza_km": 1,
      "ascesa_m": 2,
      "discesa_m": 0,
      "passo_medio": "0:04:24",
      "passo_medio_in_movimento": "0:04:24",
      "passo_migliore": "0:04:18",
      "cadenza_media_pam": 189.984375,
      "cadenza_max_pam": 193.0,
      "lunghezza_media_passo": 120.19000244140625,
      "fc_media_bpm": 165.0,
      "fc_max_bpm": 168.0,
      "temperatura_med": 23,
      "calorie": 62
    },
    {
      "lap": 5,
      "tempo": "00:04:25.911",
      "tempo_in_movimento": "00:04:25.911",
      "distanza_km": 1,
      "ascesa_m": 1,
      "discesa_m": 2,
      "passo_medio": "0:04:25",
      "passo_medio_in_movimento": "0:04:25",
      "passo_migliore": "0:04:19",
      "cadenza_media_pam": 190.3125,
      "cadenza_max_pam": 193.0,
      "lunghezza_media_passo": 118.95,
      "fc_media_bpm": 167.0,
      "fc_max_bpm": 169.0,
      "temperatura_med": 23,
      "calorie": 63
    },
    {
      "lap": 6,
      "tempo": "00:04:29.235",
      "tempo_in_movimento": "00:04:29.000",
      "distanza_km": 1,
      "ascesa_m": 3,
      "discesa_m": 7,
      "passo_medio": "0:04:29",
      "passo_medio_in_movimento": "0:04:29",
      "passo_migliore": "0:04:20",
      "cadenza_media_pam": 189.640625,
      "cadenza_max_pam": 192.0,
      "lunghezza_media_passo": 118.64000244140625,
      "fc_media_bpm": 168.0,
      "fc_max_bpm": 170.0,
      "temperatura_med": 23,
      "calorie": 64
    },
    {
      "lap": 7,
      "tempo": "00:04:30.447",
      "tempo_in_movimento": "00:04:30.000",
      "distanza_km": 1,
      "ascesa_m": 0,
      "discesa_m": 5,
      "passo_medio": "0:04:30",
      "passo_medio_in_movimento": "0:04:30",
      "passo_migliore": "0:04:16",
      "cadenza_media_pam": 182.625,
      "cadenza_max_pam": 191.0,
      "lunghezza_media_passo": 121.14000244140625,
      "fc_media_bpm": 168.0,
      "fc_max_bpm": 170.0,
      "temperatura_med": 23,
      "calorie": 63
    },
    {
      "lap": 8,
      "tempo": "00:02:00.435",
      "tempo_in_movimento": "00:02:00.000",
      "distanza_km": 0.2,
      "ascesa_m": 0,
      "discesa_m": 6,
      "passo_medio": "0:09:56",
      "passo_medio_in_movimento": "0:09:53",
      "passo_migliore": "0:04:06",
      "cadenza_media_pam": 119.546875,
      "cadenza_max_pam": 184.0,
      "lunghezza_media_passo": 90.02000122070314,
      "fc_media_bpm": 143.0,
      "fc_max_bpm": 169.0,
      "temperatura_med": 23,
      "calorie": 17
    },
    {
      "lap": 9,
      "tempo": "00:06:04.529",
      "tempo_in_movimento": "00:06:04.529",
      "distanza_km": 1,
      "ascesa_m": 3,
      "discesa_m": 6,
      "passo_medio": "0:06:04",
      "passo_medio_in_movimento": "0:06:04",
      "passo_migliore": "0:05:29",
      "cadenza_media_pam": 174.828125,
      "cadenza_max_pam": 178.0,
      "lunghezza_media_passo": 92.60000000000001,
      "fc_media_bpm": 147.0,
      "fc_max_bpm": 155.0,
      "temperatura_med": 24,
      "calorie": 67
    },
    {
      "lap": 10,
      "tempo": "00:06:14.495",
      "tempo_in_movimento": "00:06:14.495",
      "distanza_km": 1,
      "ascesa_m": 7,
      "discesa_m": 0,
      "passo_medio": "0:06:14",
      "passo_medio_in_movimento": "0:06:14",
      "passo_migliore": "0:05:12",
      "cadenza_media_pam": 174.765625,
      "cadenza_max_pam": 180.0,
      "lunghezza_media_passo": 91.57000122070313,
      "fc_media_bpm": 149.0,
      "fc_max_bpm": 152.0,
      "temperatura_med": 25,
      "calorie": 71
    },
    {
      "lap": 11,
      "tempo": "00:06:32.240",
      "tempo_in_movimento": "00:06:32.000",
      "distanza_km": 1,
      "ascesa_m": 13,
      "discesa_m": 4,
      "passo_medio": "0:06:32",
      "passo_medio_in_movimento": "0:06:32",
      "passo_migliore": "0:04:54",
      "cadenza_media_pam": 169.890625,
      "cadenza_max_pam": 178.0,
      "lunghezza_media_passo": 91.00999755859375,
      "fc_media_bpm": 146.0,
      "fc_max_bpm": 153.0,
      "temperatura_med": 25,
      "calorie": 70
    },
    {
      "lap": 12,
      "tempo": "00:06:14.590",
      "tempo_in_movimento": "00:06:14.590",
      "distanza_km": 1,
      "ascesa_m": 1,
      "discesa_m": 1,
      "passo_medio": "0:06:14",
      "passo_medio_in_movimento": "0:06:14",
      "passo_migliore": "0:04:47",
      "cadenza_media_pam": 174.265625,
      "cadenza_max_pam": 177.0,
      "lunghezza_media_passo": 93.17999877929688,
      "fc_media_bpm": 144.0,
      "fc_max_bpm": 148.0,
      "temperatura_med": 25,
      "calorie": 66
    },
    {
      "lap": 13,
      "tempo": "00:06:17.321",
      "tempo_in_movimento": "00:06:17.000",
      "distanza_km": 1,
      "ascesa_m": 3,
      "discesa_m": 4,
      "passo_medio": "0:06:17",
      "passo_medio_in_movimento": "0:06:17",
      "passo_migliore": "0:05:36",
      "cadenza_media_pam": 173.125,
      "cadenza_max_pam": 177.0,
      "lunghezza_media_passo": 92.32000122070313,
      "fc_media_bpm": 141.0,
      "fc_max_bpm": 145.0,
      "temperatura_med": 25,
      "calorie": 67
    },
    {
      "lap": 14,
      "tempo": "00:05:36.913",
      "tempo_in_movimento": "00:05:36.000",
      "distanza_km": 0.91,
      "ascesa_m": 10,
      "discesa_m": 0,
      "passo_medio": "0:06:12",
      "passo_medio_in_movimento": "0:06:11",
      "passo_migliore": "0:05:40",
      "cadenza_media_pam": 172.78125,
      "cadenza_max_pam": 176.0,
      "lunghezza_media_passo": 93.60000000000001,
      "fc_media_bpm": 142.0,
      "fc_max_bpm": 146.0,
      "temperatura_med": 25,
      "calorie": 64
    }
  ],
  "summary": {
    "lap": "Summary",
    "tempo": "01:13:07.304",
    "tempo_in_movimento": "01:13:03.681",
    "distanza_km": 13.11,
    "ascesa_m": 53,
    "discesa_m": 50,
    "passo_medio": "0:05:34",
    "passo_medio_in_movimento": "0:05:34",
    "passo_migliore": "0:04:02",
    "cadenza_media_pam": 176.703125,
    "cadenza_max_pam": 193.0,
    "lunghezza_media_passo": 101.20999755859376,
    "fc_media_bpm": 150.0,
    "fc_max_bpm": 170.0,
    "temperatura_med": 24.72,
    "calorie": 871
  }
}